<?xml version="1.0" encoding="utf-8"?><index><stem n="rofile"><phr n="profile"><ent r="4" t="100" w="146" /><ent r="4" t="100" w="175" /><ent r="4" t="100" w="175" /><ent r="4" t="100" w="202" /><ent r="4" t="100" w="202" /><ent r="65" t="100" w="228" /><ent r="65" t="100" w="228" /><ent r="4" t="100" w="237" /><ent r="4" t="100" w="237" /><ent r="4" t="100" w="282" /><ent r="3" t="101" w="65" /><ent r="3" t="101" w="65" /><ent r="65" t="101" w="194" /><ent r="65" t="101" w="194" /><ent r="3" t="102" w="291" /><ent r="3" t="102" w="291" /><ent r="65" t="103" w="279" /><ent r="65" t="103" w="279" /><ent r="65" t="103" w="414" /><ent r="65" t="103" w="414" /><ent r="5" t="118" w="83" /><ent r="5" t="118" w="83" /><ent r="6" t="118" w="98" /><ent r="6" t="118" w="98" /><ent r="5" t="118" w="170" /><ent r="5" t="118" w="200" /><ent r="5" t="118" w="200" /><ent r="64" t="118" w="282" /><ent r="64" t="118" w="282" /><ent r="3" t="119" w="67" /><ent r="3" t="119" w="67" /><ent r="4" t="119" w="114" /><ent r="6" t="119" w="181" /><ent r="6" t="119" w="192" /><ent r="64" t="119" w="211" /><ent r="64" t="119" w="211" /><ent r="65" t="123" w="110" /><ent r="65" t="123" w="110" /><ent r="65" t="123" w="189" /><ent r="65" t="123" w="189" /><ent r="3" t="124" w="26" /><ent r="4" t="127" w="127" /><ent r="4" t="127" w="127" /><ent r="4" t="127" w="132" /><ent r="4" t="127" w="132" /><ent r="3" t="128" w="138" /><ent r="3" t="128" w="138" /><ent r="3" t="128" w="148" /><ent r="3" t="128" w="148" /><ent r="3" t="128" w="167" /><ent r="3" t="128" w="167" /><ent r="3" t="128" w="178" /><ent r="3" t="128" w="181" /><ent r="3" t="128" w="181" /><ent r="3" t="128" w="202" /><ent r="3" t="128" w="202" /><ent r="4" t="128" w="327" /><ent r="4" t="128" w="327" /><ent r="4" t="128" w="332" /><ent r="4" t="128" w="332" /><ent r="3" t="132" w="219" /><ent r="6" t="133" w="34" /><ent r="6" t="133" w="34" /><ent r="100" t="136" w="26" /><ent r="100" t="136" w="26" /><ent r="3" t="136" w="59" /><ent r="4" t="136" w="109" /><ent r="67" t="140" w="162" /><ent r="67" t="140" w="162" /><ent r="3" t="141" w="223" /><ent r="6" t="143" w="40" /><ent r="6" t="143" w="40" /><ent r="100" t="144" w="8" /><ent r="100" t="144" w="8" /><ent r="100" t="144" w="16" /><ent r="100" t="144" w="16" /><ent r="3" t="144" w="30" /><ent r="3" t="144" w="30" /><ent r="3" t="144" w="60" /><ent r="3" t="144" w="60" /><ent r="3" t="144" w="72" /><ent r="3" t="146" w="79" /><ent r="3" t="146" w="79" /><ent r="4" t="147" w="159" /><ent r="4" t="147" w="159" /><ent r="4" t="147" w="179" /><ent r="4" t="147" w="179" /><ent r="7" t="147" w="221" /><ent r="7" t="147" w="221" /><ent r="4" t="147" w="270" /><ent r="4" t="147" w="295" /><ent r="65" t="147" w="433" /><ent r="100" t="149" w="53" /><ent r="100" t="149" w="53" /><ent r="100" t="149" w="63" /><ent r="100" t="149" w="63" /><ent r="4" t="149" w="95" /><ent r="4" t="149" w="95" /><ent r="4" t="149" w="275" /><ent r="100" t="151" w="12" /><ent r="100" t="151" w="12" /><ent r="100" t="151" w="23" /><ent r="100" t="151" w="23" /><ent r="100" t="151" w="32" /><ent r="100" t="151" w="32" /><ent r="3" t="151" w="51" /><ent r="3" t="151" w="51" /><ent r="3" t="151" w="165" /><ent r="3" t="151" w="165" /><ent r="4" t="151" w="182" /><ent r="4" t="151" w="182" /><ent r="4" t="151" w="218" /><ent r="4" t="151" w="218" /><ent r="4" t="151" w="246" /><ent r="4" t="151" w="367" /><ent r="4" t="151" w="367" /><ent r="6" t="152" w="65" /><ent r="6" t="152" w="65" /><ent r="65" t="152" w="129" /><ent r="65" t="152" w="129" /><ent r="3" t="153" w="91" /><ent r="3" t="153" w="91" /><ent r="3" t="153" w="109" /><ent r="3" t="153" w="109" /><ent r="4" t="153" w="224" /><ent r="4" t="153" w="224" /><ent r="4" t="153" w="245" /><ent r="4" t="153" w="245" /><ent r="4" t="153" w="302" /><ent r="4" t="153" w="327" /><ent r="65" t="153" w="448" /><ent r="65" t="153" w="448" /><ent r="3" t="153" w="458" /><ent r="3" t="153" w="458" /><ent r="3" t="156" w="64" /><ent r="3" t="156" w="64" /><ent r="3" t="157" w="61" /><ent r="3" t="157" w="61" /><ent r="3" t="157" w="509" /><ent r="3" t="157" w="509" /><ent r="3" t="159" w="221" /><ent r="100" t="163" w="14" /><ent r="100" t="163" w="14" /><ent r="3" t="164" w="81" /><ent r="4" t="164" w="141" /><ent r="4" t="164" w="141" /><ent r="4" t="164" w="164" /><ent r="4" t="164" w="164" /><ent r="3" t="166" w="52" /><ent r="100" t="166" w="97" /><ent r="100" t="166" w="97" /><ent r="4" t="166" w="114" /><ent r="4" t="166" w="114" /><ent r="4" t="167" w="109" /><ent r="5" t="168" w="258" /><ent r="5" t="168" w="258" /><ent r="6" t="168" w="284" /><ent r="6" t="168" w="284" /><ent r="6" t="168" w="301" /><ent r="6" t="168" w="301" /><ent r="3" t="169" w="85" /><ent r="3" t="170" w="50" /><ent r="3" t="170" w="50" /><ent r="5" t="170" w="156" /><ent r="5" t="170" w="156" /><ent r="6" t="170" w="192" /><ent r="6" t="170" w="192" /><ent r="6" t="170" w="202" /><ent r="6" t="170" w="202" /><ent r="3" t="171" w="77" /><ent r="3" t="171" w="77" /><ent r="5" t="171" w="176" /><ent r="5" t="171" w="176" /><ent r="6" t="171" w="202" /><ent r="6" t="171" w="202" /><ent r="6" t="171" w="219" /><ent r="6" t="171" w="219" /><ent r="3" t="319" w="37" /><ent r="3" t="319" w="37" /><ent r="8" t="346" w="623" /><ent r="8" t="346" w="623" /><ent r="4" t="600" w="122" /><ent r="4" t="600" w="122" /></phr><phr n="profiles"><ent r="4" t="100" w="157" /><ent r="3" t="118" w="47" /><ent r="4" t="119" w="148" /><ent r="4" t="119" w="148" /><ent r="4" t="119" w="158" /><ent r="4" t="119" w="158" /><ent r="3" t="128" w="230" /><ent r="3" t="128" w="230" /><ent r="3" t="128" w="244" /><ent r="3" t="128" w="244" /><ent r="3" t="128" w="263" /><ent r="3" t="128" w="263" /><ent r="3" t="136" w="65" /><ent r="3" t="136" w="113" /><ent r="3" t="136" w="113" /><ent r="3" t="145" w="69" /><ent r="3" t="145" w="69" /><ent r="3" t="156" w="48" /><ent r="3" t="156" w="48" /><ent r="3" t="156" w="92" /><ent r="3" t="156" w="92" /><ent r="3" t="156" w="106" /><ent r="3" t="156" w="106" /><ent r="6" t="156" w="112" /><ent r="6" t="156" w="112" /><ent r="3" t="156" w="123" /><ent r="3" t="156" w="123" /><ent r="4" t="166" w="131" /><ent r="4" t="166" w="131" /><ent r="100" t="167" w="13" /><ent r="100" t="167" w="13" /><ent r="100" t="168" w="7" /><ent r="100" t="168" w="7" /><ent r="100" t="172" w="15" /><ent r="100" t="172" w="15" /></phr><phr n="Profile"><ent r="4" t="101" w="202" /><ent r="67" t="118" w="269" /><ent r="67" t="118" w="269" /><ent r="67" t="118" w="272" /><ent r="67" t="118" w="272" /><ent r="1000" t="119" w="6" /><ent r="1000" t="119" w="6" /><ent r="100" t="119" w="9" /><ent r="100" t="119" w="13" /><ent r="102" t="119" w="21" /><ent r="102" t="119" w="21" /><ent r="3" t="119" w="50" /><ent r="3" t="119" w="50" /><ent r="3" t="119" w="59" /><ent r="5" t="119" w="91" /><ent r="5" t="119" w="91" /><ent r="5" t="119" w="96" /><ent r="5" t="119" w="96" /><ent r="5" t="119" w="119" /><ent r="5" t="119" w="119" /><ent r="5" t="123" w="81" /><ent r="5" t="123" w="81" /><ent r="5" t="123" w="102" /><ent r="5" t="123" w="102" /><ent r="5" t="123" w="169" /><ent r="5" t="123" w="169" /><ent r="5" t="123" w="181" /><ent r="5" t="123" w="181" /><ent r="64" t="123" w="220" /><ent r="64" t="123" w="220" /><ent r="5" t="127" w="121" /><ent r="5" t="127" w="121" /><ent r="5" t="128" w="321" /><ent r="5" t="128" w="321" /><ent r="64" t="128" w="418" /><ent r="64" t="128" w="418" /><ent r="6" t="133" w="31" /><ent r="6" t="133" w="31" /><ent r="1000" t="136" w="4" /><ent r="1000" t="136" w="4" /><ent r="102" t="136" w="12" /><ent r="102" t="136" w="12" /><ent r="5" t="136" w="94" /><ent r="5" t="136" w="94" /><ent r="5" t="136" w="160" /><ent r="5" t="136" w="160" /><ent r="4" t="136" w="185" /><ent r="4" t="136" w="185" /><ent r="64" t="136" w="209" /><ent r="64" t="136" w="209" /><ent r="64" t="139" w="95" /><ent r="64" t="139" w="95" /><ent r="7" t="140" w="151" /><ent r="7" t="140" w="151" /><ent r="64" t="140" w="210" /><ent r="64" t="140" w="210" /><ent r="64" t="142" w="196" /><ent r="64" t="142" w="196" /><ent r="6" t="143" w="37" /><ent r="6" t="143" w="37" /><ent r="1000" t="144" w="3" /><ent r="1000" t="144" w="3" /><ent r="102" t="144" w="20" /><ent r="102" t="144" w="20" /><ent r="3" t="144" w="25" /><ent r="3" t="144" w="25" /><ent r="3" t="144" w="68" /><ent r="64" t="145" w="149" /><ent r="64" t="145" w="149" /><ent r="5" t="147" w="188" /><ent r="5" t="147" w="188" /><ent r="64" t="147" w="501" /><ent r="64" t="147" w="501" /><ent r="1000" t="149" w="5" /><ent r="1000" t="149" w="5" /><ent r="102" t="149" w="11" /><ent r="102" t="149" w="11" /><ent r="100" t="149" w="55" /><ent r="1000" t="151" w="2" /><ent r="1000" t="151" w="2" /><ent r="102" t="151" w="6" /><ent r="102" t="151" w="6" /><ent r="100" t="151" w="14" /><ent r="5" t="151" w="200" /><ent r="5" t="151" w="200" /><ent r="5" t="151" w="207" /><ent r="5" t="151" w="207" /><ent r="5" t="153" w="255" /><ent r="5" t="153" w="255" /><ent r="4" t="156" w="140" /><ent r="4" t="156" w="140" /><ent r="4" t="156" w="160" /><ent r="4" t="156" w="160" /><ent r="5" t="156" w="183" /><ent r="5" t="156" w="183" /><ent r="4" t="156" w="194" /><ent r="4" t="156" w="194" /><ent r="65" t="156" w="215" /><ent r="65" t="156" w="215" /><ent r="64" t="158" w="109" /><ent r="64" t="158" w="109" /><ent r="68" t="159" w="183" /><ent r="68" t="159" w="183" /><ent r="1000" t="160" w="2" /><ent r="1000" t="160" w="2" /><ent r="64" t="160" w="403" /><ent r="64" t="160" w="403" /><ent r="64" t="161" w="170" /><ent r="64" t="161" w="170" /><ent r="1000" t="162" w="2" /><ent r="1000" t="162" w="2" /><ent r="64" t="162" w="190" /><ent r="64" t="162" w="190" /><ent r="1000" t="163" w="2" /><ent r="1000" t="163" w="2" /><ent r="64" t="163" w="104" /><ent r="64" t="163" w="104" /><ent r="64" t="164" w="436" /><ent r="64" t="164" w="436" /><ent r="1000" t="166" w="2" /><ent r="1000" t="166" w="2" /><ent r="5" t="166" w="108" /><ent r="5" t="166" w="108" /><ent r="64" t="166" w="226" /><ent r="64" t="166" w="226" /><ent r="1000" t="167" w="2" /><ent r="1000" t="167" w="2" /><ent r="64" t="167" w="549" /><ent r="64" t="167" w="549" /><ent r="1000" t="168" w="2" /><ent r="1000" t="168" w="2" /><ent r="7" t="168" w="264" /><ent r="7" t="168" w="264" /><ent r="64" t="168" w="360" /><ent r="64" t="168" w="360" /><ent r="1000" t="169" w="2" /><ent r="1000" t="169" w="2" /><ent r="64" t="169" w="450" /><ent r="64" t="169" w="450" /><ent r="7" t="170" w="172" /><ent r="7" t="170" w="172" /><ent r="64" t="170" w="268" /><ent r="64" t="170" w="268" /><ent r="7" t="171" w="182" /><ent r="7" t="171" w="182" /><ent r="64" t="171" w="281" /><ent r="64" t="171" w="281" /><ent r="1000" t="172" w="2" /><ent r="1000" t="172" w="2" /><ent r="100" t="172" w="7" /><ent r="100" t="172" w="7" /></phr><phr n="USERPROFILE"><ent r="7" t="572" w="49" /><ent r="7" t="572" w="49" /></phr></stem><stem n="profile"><phr n="profile"><ent r="4" t="100" w="146" /><ent r="4" t="100" w="175" /><ent r="4" t="100" w="175" /><ent r="4" t="100" w="202" /><ent r="4" t="100" w="202" /><ent r="65" t="100" w="228" /><ent r="65" t="100" w="228" /><ent r="4" t="100" w="237" /><ent r="4" t="100" w="237" /><ent r="4" t="100" w="282" /><ent r="3" t="101" w="65" /><ent r="3" t="101" w="65" /><ent r="65" t="101" w="194" /><ent r="65" t="101" w="194" /><ent r="3" t="102" w="291" /><ent r="3" t="102" w="291" /><ent r="65" t="103" w="279" /><ent r="65" t="103" w="279" /><ent r="65" t="103" w="414" /><ent r="65" t="103" w="414" /><ent r="5" t="118" w="83" /><ent r="5" t="118" w="83" /><ent r="6" t="118" w="98" /><ent r="6" t="118" w="98" /><ent r="5" t="118" w="170" /><ent r="5" t="118" w="200" /><ent r="5" t="118" w="200" /><ent r="64" t="118" w="282" /><ent r="64" t="118" w="282" /><ent r="3" t="119" w="67" /><ent r="3" t="119" w="67" /><ent r="4" t="119" w="114" /><ent r="6" t="119" w="181" /><ent r="6" t="119" w="192" /><ent r="64" t="119" w="211" /><ent r="64" t="119" w="211" /><ent r="65" t="123" w="110" /><ent r="65" t="123" w="110" /><ent r="65" t="123" w="189" /><ent r="65" t="123" w="189" /><ent r="3" t="124" w="26" /><ent r="4" t="127" w="127" /><ent r="4" t="127" w="127" /><ent r="4" t="127" w="132" /><ent r="4" t="127" w="132" /><ent r="3" t="128" w="138" /><ent r="3" t="128" w="138" /><ent r="3" t="128" w="148" /><ent r="3" t="128" w="148" /><ent r="3" t="128" w="167" /><ent r="3" t="128" w="167" /><ent r="3" t="128" w="178" /><ent r="3" t="128" w="181" /><ent r="3" t="128" w="181" /><ent r="3" t="128" w="202" /><ent r="3" t="128" w="202" /><ent r="4" t="128" w="327" /><ent r="4" t="128" w="327" /><ent r="4" t="128" w="332" /><ent r="4" t="128" w="332" /><ent r="3" t="132" w="219" /><ent r="6" t="133" w="34" /><ent r="6" t="133" w="34" /><ent r="100" t="136" w="26" /><ent r="100" t="136" w="26" /><ent r="3" t="136" w="59" /><ent r="4" t="136" w="109" /><ent r="67" t="140" w="162" /><ent r="67" t="140" w="162" /><ent r="3" t="141" w="223" /><ent r="6" t="143" w="40" /><ent r="6" t="143" w="40" /><ent r="100" t="144" w="8" /><ent r="100" t="144" w="8" /><ent r="100" t="144" w="16" /><ent r="100" t="144" w="16" /><ent r="3" t="144" w="30" /><ent r="3" t="144" w="30" /><ent r="3" t="144" w="60" /><ent r="3" t="144" w="60" /><ent r="3" t="144" w="72" /><ent r="3" t="146" w="79" /><ent r="3" t="146" w="79" /><ent r="4" t="147" w="159" /><ent r="4" t="147" w="159" /><ent r="4" t="147" w="179" /><ent r="4" t="147" w="179" /><ent r="7" t="147" w="221" /><ent r="7" t="147" w="221" /><ent r="4" t="147" w="270" /><ent r="4" t="147" w="295" /><ent r="65" t="147" w="433" /><ent r="100" t="149" w="53" /><ent r="100" t="149" w="53" /><ent r="100" t="149" w="63" /><ent r="100" t="149" w="63" /><ent r="4" t="149" w="95" /><ent r="4" t="149" w="95" /><ent r="4" t="149" w="275" /><ent r="100" t="151" w="12" /><ent r="100" t="151" w="12" /><ent r="100" t="151" w="23" /><ent r="100" t="151" w="23" /><ent r="100" t="151" w="32" /><ent r="100" t="151" w="32" /><ent r="3" t="151" w="51" /><ent r="3" t="151" w="51" /><ent r="3" t="151" w="165" /><ent r="3" t="151" w="165" /><ent r="4" t="151" w="182" /><ent r="4" t="151" w="182" /><ent r="4" t="151" w="218" /><ent r="4" t="151" w="218" /><ent r="4" t="151" w="246" /><ent r="4" t="151" w="367" /><ent r="4" t="151" w="367" /><ent r="6" t="152" w="65" /><ent r="6" t="152" w="65" /><ent r="65" t="152" w="129" /><ent r="65" t="152" w="129" /><ent r="3" t="153" w="91" /><ent r="3" t="153" w="91" /><ent r="3" t="153" w="109" /><ent r="3" t="153" w="109" /><ent r="4" t="153" w="224" /><ent r="4" t="153" w="224" /><ent r="4" t="153" w="245" /><ent r="4" t="153" w="245" /><ent r="4" t="153" w="302" /><ent r="4" t="153" w="327" /><ent r="65" t="153" w="448" /><ent r="65" t="153" w="448" /><ent r="3" t="153" w="458" /><ent r="3" t="153" w="458" /><ent r="3" t="156" w="64" /><ent r="3" t="156" w="64" /><ent r="3" t="157" w="61" /><ent r="3" t="157" w="61" /><ent r="3" t="157" w="509" /><ent r="3" t="157" w="509" /><ent r="3" t="159" w="221" /><ent r="100" t="163" w="14" /><ent r="100" t="163" w="14" /><ent r="3" t="164" w="81" /><ent r="4" t="164" w="141" /><ent r="4" t="164" w="141" /><ent r="4" t="164" w="164" /><ent r="4" t="164" w="164" /><ent r="3" t="166" w="52" /><ent r="100" t="166" w="97" /><ent r="100" t="166" w="97" /><ent r="4" t="166" w="114" /><ent r="4" t="166" w="114" /><ent r="4" t="167" w="109" /><ent r="5" t="168" w="258" /><ent r="5" t="168" w="258" /><ent r="6" t="168" w="284" /><ent r="6" t="168" w="284" /><ent r="6" t="168" w="301" /><ent r="6" t="168" w="301" /><ent r="3" t="169" w="85" /><ent r="3" t="170" w="50" /><ent r="3" t="170" w="50" /><ent r="5" t="170" w="156" /><ent r="5" t="170" w="156" /><ent r="6" t="170" w="192" /><ent r="6" t="170" w="192" /><ent r="6" t="170" w="202" /><ent r="6" t="170" w="202" /><ent r="3" t="171" w="77" /><ent r="3" t="171" w="77" /><ent r="5" t="171" w="176" /><ent r="5" t="171" w="176" /><ent r="6" t="171" w="202" /><ent r="6" t="171" w="202" /><ent r="6" t="171" w="219" /><ent r="6" t="171" w="219" /><ent r="3" t="319" w="37" /><ent r="3" t="319" w="37" /><ent r="8" t="346" w="623" /><ent r="8" t="346" w="623" /><ent r="4" t="600" w="122" /><ent r="4" t="600" w="122" /></phr><phr n="profiles"><ent r="4" t="100" w="157" /><ent r="3" t="118" w="47" /><ent r="4" t="119" w="148" /><ent r="4" t="119" w="148" /><ent r="4" t="119" w="158" /><ent r="4" t="119" w="158" /><ent r="3" t="128" w="230" /><ent r="3" t="128" w="230" /><ent r="3" t="128" w="244" /><ent r="3" t="128" w="244" /><ent r="3" t="128" w="263" /><ent r="3" t="128" w="263" /><ent r="3" t="136" w="65" /><ent r="3" t="136" w="113" /><ent r="3" t="136" w="113" /><ent r="3" t="145" w="69" /><ent r="3" t="145" w="69" /><ent r="3" t="156" w="48" /><ent r="3" t="156" w="48" /><ent r="3" t="156" w="92" /><ent r="3" t="156" w="92" /><ent r="3" t="156" w="106" /><ent r="3" t="156" w="106" /><ent r="6" t="156" w="112" /><ent r="6" t="156" w="112" /><ent r="3" t="156" w="123" /><ent r="3" t="156" w="123" /><ent r="4" t="166" w="131" /><ent r="4" t="166" w="131" /><ent r="100" t="167" w="13" /><ent r="100" t="167" w="13" /><ent r="100" t="168" w="7" /><ent r="100" t="168" w="7" /><ent r="100" t="172" w="15" /><ent r="100" t="172" w="15" /></phr><phr n="Profile"><ent r="4" t="101" w="202" /><ent r="67" t="118" w="269" /><ent r="67" t="118" w="269" /><ent r="67" t="118" w="272" /><ent r="67" t="118" w="272" /><ent r="1000" t="119" w="6" /><ent r="1000" t="119" w="6" /><ent r="100" t="119" w="9" /><ent r="100" t="119" w="13" /><ent r="102" t="119" w="21" /><ent r="102" t="119" w="21" /><ent r="3" t="119" w="50" /><ent r="3" t="119" w="50" /><ent r="3" t="119" w="59" /><ent r="5" t="119" w="91" /><ent r="5" t="119" w="91" /><ent r="5" t="119" w="96" /><ent r="5" t="119" w="96" /><ent r="5" t="119" w="119" /><ent r="5" t="119" w="119" /><ent r="5" t="123" w="81" /><ent r="5" t="123" w="81" /><ent r="5" t="123" w="102" /><ent r="5" t="123" w="102" /><ent r="5" t="123" w="169" /><ent r="5" t="123" w="169" /><ent r="5" t="123" w="181" /><ent r="5" t="123" w="181" /><ent r="64" t="123" w="220" /><ent r="64" t="123" w="220" /><ent r="5" t="127" w="121" /><ent r="5" t="127" w="121" /><ent r="5" t="128" w="321" /><ent r="5" t="128" w="321" /><ent r="64" t="128" w="418" /><ent r="64" t="128" w="418" /><ent r="6" t="133" w="31" /><ent r="6" t="133" w="31" /><ent r="1000" t="136" w="4" /><ent r="1000" t="136" w="4" /><ent r="102" t="136" w="12" /><ent r="102" t="136" w="12" /><ent r="5" t="136" w="94" /><ent r="5" t="136" w="94" /><ent r="5" t="136" w="160" /><ent r="5" t="136" w="160" /><ent r="4" t="136" w="185" /><ent r="4" t="136" w="185" /><ent r="64" t="136" w="209" /><ent r="64" t="136" w="209" /><ent r="64" t="139" w="95" /><ent r="64" t="139" w="95" /><ent r="7" t="140" w="151" /><ent r="7" t="140" w="151" /><ent r="64" t="140" w="210" /><ent r="64" t="140" w="210" /><ent r="64" t="142" w="196" /><ent r="64" t="142" w="196" /><ent r="6" t="143" w="37" /><ent r="6" t="143" w="37" /><ent r="1000" t="144" w="3" /><ent r="1000" t="144" w="3" /><ent r="102" t="144" w="20" /><ent r="102" t="144" w="20" /><ent r="3" t="144" w="25" /><ent r="3" t="144" w="25" /><ent r="3" t="144" w="68" /><ent r="64" t="145" w="149" /><ent r="64" t="145" w="149" /><ent r="5" t="147" w="188" /><ent r="5" t="147" w="188" /><ent r="64" t="147" w="501" /><ent r="64" t="147" w="501" /><ent r="1000" t="149" w="5" /><ent r="1000" t="149" w="5" /><ent r="102" t="149" w="11" /><ent r="102" t="149" w="11" /><ent r="100" t="149" w="55" /><ent r="1000" t="151" w="2" /><ent r="1000" t="151" w="2" /><ent r="102" t="151" w="6" /><ent r="102" t="151" w="6" /><ent r="100" t="151" w="14" /><ent r="5" t="151" w="200" /><ent r="5" t="151" w="200" /><ent r="5" t="151" w="207" /><ent r="5" t="151" w="207" /><ent r="5" t="153" w="255" /><ent r="5" t="153" w="255" /><ent r="4" t="156" w="140" /><ent r="4" t="156" w="140" /><ent r="4" t="156" w="160" /><ent r="4" t="156" w="160" /><ent r="5" t="156" w="183" /><ent r="5" t="156" w="183" /><ent r="4" t="156" w="194" /><ent r="4" t="156" w="194" /><ent r="65" t="156" w="215" /><ent r="65" t="156" w="215" /><ent r="64" t="158" w="109" /><ent r="64" t="158" w="109" /><ent r="68" t="159" w="183" /><ent r="68" t="159" w="183" /><ent r="1000" t="160" w="2" /><ent r="1000" t="160" w="2" /><ent r="64" t="160" w="403" /><ent r="64" t="160" w="403" /><ent r="64" t="161" w="170" /><ent r="64" t="161" w="170" /><ent r="1000" t="162" w="2" /><ent r="1000" t="162" w="2" /><ent r="64" t="162" w="190" /><ent r="64" t="162" w="190" /><ent r="1000" t="163" w="2" /><ent r="1000" t="163" w="2" /><ent r="64" t="163" w="104" /><ent r="64" t="163" w="104" /><ent r="64" t="164" w="436" /><ent r="64" t="164" w="436" /><ent r="1000" t="166" w="2" /><ent r="1000" t="166" w="2" /><ent r="5" t="166" w="108" /><ent r="5" t="166" w="108" /><ent r="64" t="166" w="226" /><ent r="64" t="166" w="226" /><ent r="1000" t="167" w="2" /><ent r="1000" t="167" w="2" /><ent r="64" t="167" w="549" /><ent r="64" t="167" w="549" /><ent r="1000" t="168" w="2" /><ent r="1000" t="168" w="2" /><ent r="7" t="168" w="264" /><ent r="7" t="168" w="264" /><ent r="64" t="168" w="360" /><ent r="64" t="168" w="360" /><ent r="1000" t="169" w="2" /><ent r="1000" t="169" w="2" /><ent r="64" t="169" w="450" /><ent r="64" t="169" w="450" /><ent r="7" t="170" w="172" /><ent r="7" t="170" w="172" /><ent r="64" t="170" w="268" /><ent r="64" t="170" w="268" /><ent r="7" t="171" w="182" /><ent r="7" t="171" w="182" /><ent r="64" t="171" w="281" /><ent r="64" t="171" w="281" /><ent r="1000" t="172" w="2" /><ent r="1000" t="172" w="2" /><ent r="100" t="172" w="7" /><ent r="100" t="172" w="7" /></phr><phr n="USERPROFILE"><ent r="7" t="572" w="49" /><ent r="7" t="572" w="49" /></phr></stem><stem n="dentic"><phr n="identical"><ent r="4" t="100" w="156" /><ent r="4" t="100" w="156" /><ent r="3" t="574" w="185" /><ent r="3" t="574" w="185" /><ent r="3" t="574" w="196" /><ent r="3" t="574" w="196" /></phr></stem><stem n="ntical"><phr n="identical"><ent r="4" t="100" w="156" /><ent r="4" t="100" w="156" /><ent r="3" t="574" w="185" /><ent r="3" t="574" w="185" /><ent r="3" t="574" w="196" /><ent r="3" t="574" w="196" /></phr></stem><stem n="identic"><phr n="identical"><ent r="4" t="100" w="156" /><ent r="4" t="100" w="156" /><ent r="3" t="574" w="185" /><ent r="3" t="574" w="185" /><ent r="3" t="574" w="196" /><ent r="3" t="574" w="196" /></phr></stem><stem n="dentica"><phr n="identical"><ent r="4" t="100" w="156" /><ent r="4" t="100" w="156" /><ent r="3" t="574" w="185" /><ent r="3" t="574" w="185" /><ent r="3" t="574" w="196" /><ent r="3" t="574" w="196" /></phr></stem><stem n="entical"><phr n="identical"><ent r="4" t="100" w="156" /><ent r="4" t="100" w="156" /><ent r="3" t="574" w="185" /><ent r="3" t="574" w="185" /><ent r="3" t="574" w="196" /><ent r="3" t="574" w="196" /></phr></stem><stem n="identica"><phr n="identical"><ent r="4" t="100" w="156" /><ent r="4" t="100" w="156" /><ent r="3" t="574" w="185" /><ent r="3" t="574" w="185" /><ent r="3" t="574" w="196" /><ent r="3" t="574" w="196" /></phr></stem><stem n="dentical"><phr n="identical"><ent r="4" t="100" w="156" /><ent r="4" t="100" w="156" /><ent r="3" t="574" w="185" /><ent r="3" t="574" w="185" /><ent r="3" t="574" w="196" /><ent r="3" t="574" w="196" /></phr></stem><stem n="identical"><phr n="identical"><ent r="4" t="100" w="156" /><ent r="4" t="100" w="156" /><ent r="3" t="574" w="185" /><ent r="3" t="574" w="185" /><ent r="3" t="574" w="196" /><ent r="3" t="574" w="196" /></phr></stem><stem n="ofiles"><phr n="profiles"><ent r="4" t="100" w="157" /><ent r="3" t="118" w="47" /><ent r="4" t="119" w="148" /><ent r="4" t="119" w="148" /><ent r="4" t="119" w="158" /><ent r="4" t="119" w="158" /><ent r="3" t="128" w="230" /><ent r="3" t="128" w="230" /><ent r="3" t="128" w="244" /><ent r="3" t="128" w="244" /><ent r="3" t="128" w="263" /><ent r="3" t="128" w="263" /><ent r="3" t="136" w="65" /><ent r="3" t="136" w="113" /><ent r="3" t="136" w="113" /><ent r="3" t="145" w="69" /><ent r="3" t="145" w="69" /><ent r="3" t="156" w="48" /><ent r="3" t="156" w="48" /><ent r="3" t="156" w="92" /><ent r="3" t="156" w="92" /><ent r="3" t="156" w="106" /><ent r="3" t="156" w="106" /><ent r="6" t="156" w="112" /><ent r="6" t="156" w="112" /><ent r="3" t="156" w="123" /><ent r="3" t="156" w="123" /><ent r="4" t="166" w="131" /><ent r="4" t="166" w="131" /><ent r="100" t="167" w="13" /><ent r="100" t="167" w="13" /><ent r="100" t="168" w="7" /><ent r="100" t="168" w="7" /><ent r="100" t="172" w="15" /><ent r="100" t="172" w="15" /></phr></stem><stem n="rofiles"><phr n="profiles"><ent r="4" t="100" w="157" /><ent r="3" t="118" w="47" /><ent r="4" t="119" w="148" /><ent r="4" t="119" w="148" /><ent r="4" t="119" w="158" /><ent r="4" t="119" w="158" /><ent r="3" t="128" w="230" /><ent r="3" t="128" w="230" /><ent r="3" t="128" w="244" /><ent r="3" t="128" w="244" /><ent r="3" t="128" w="263" /><ent r="3" t="128" w="263" /><ent r="3" t="136" w="65" /><ent r="3" t="136" w="113" /><ent r="3" t="136" w="113" /><ent r="3" t="145" w="69" /><ent r="3" t="145" w="69" /><ent r="3" t="156" w="48" /><ent r="3" t="156" w="48" /><ent r="3" t="156" w="92" /><ent r="3" t="156" w="92" /><ent r="3" t="156" w="106" /><ent r="3" t="156" w="106" /><ent r="6" t="156" w="112" /><ent r="6" t="156" w="112" /><ent r="3" t="156" w="123" /><ent r="3" t="156" w="123" /><ent r="4" t="166" w="131" /><ent r="4" t="166" w="131" /><ent r="100" t="167" w="13" /><ent r="100" t="167" w="13" /><ent r="100" t="168" w="7" /><ent r="100" t="168" w="7" /><ent r="100" t="172" w="15" /><ent r="100" t="172" w="15" /></phr></stem><stem n="profiles"><phr n="profiles"><ent r="4" t="100" w="157" /><ent r="3" t="118" w="47" /><ent r="4" t="119" w="148" /><ent r="4" t="119" w="148" /><ent r="4" t="119" w="158" /><ent r="4" t="119" w="158" /><ent r="3" t="128" w="230" /><ent r="3" t="128" w="230" /><ent r="3" t="128" w="244" /><ent r="3" t="128" w="244" /><ent r="3" t="128" w="263" /><ent r="3" t="128" w="263" /><ent r="3" t="136" w="65" /><ent r="3" t="136" w="113" /><ent r="3" t="136" w="113" /><ent r="3" t="145" w="69" /><ent r="3" t="145" w="69" /><ent r="3" t="156" w="48" /><ent r="3" t="156" w="48" /><ent r="3" t="156" w="92" /><ent r="3" t="156" w="92" /><ent r="3" t="156" w="106" /><ent r="3" t="156" w="106" /><ent r="6" t="156" w="112" /><ent r="6" t="156" w="112" /><ent r="3" t="156" w="123" /><ent r="3" t="156" w="123" /><ent r="4" t="166" w="131" /><ent r="4" t="166" w="131" /><ent r="100" t="167" w="13" /><ent r="100" t="167" w="13" /><ent r="100" t="168" w="7" /><ent r="100" t="168" w="7" /><ent r="100" t="172" w="15" /><ent r="100" t="172" w="15" /></phr></stem></index>